pyholos/__init__.py
pyholos/common.py
pyholos/common2.py
pyholos/config.py
pyholos/core_constants.py
pyholos/defaults.py
pyholos/launching.py
pyholos/soil.py
pyholos/utils.py
pyholos/version.py
pyholos/components/__init__.py
pyholos/components/common.py
pyholos/components/animals/__init__.py
pyholos/components/animals/beef.py
pyholos/components/animals/common.py
pyholos/components/animals/dairy.py
pyholos/components/animals/sheep.py
pyholos/components/land_management/__init__.py
pyholos/components/land_management/common.py
pyholos/components/land_management/crop.py
pyholos/components/land_management/field_system.py
pyholos/components/land_management/utils.py
pyholos/components/land_management/carbon/__init__.py
pyholos/components/land_management/carbon/climate.py
pyholos/components/land_management/carbon/management.py
pyholos/components/land_management/carbon/relative_biomass_information.py
pyholos/components/land_management/carbon/tillage.py
pyholos/farm/__init__.py
pyholos/farm/enums.py
pyholos/farm/farm.py
pyholos/farm/farm_inputs.py
pyholos/farm/farm_settings.py
pyholos/postprocessing/__init__.py
pyholos/postprocessing/plots.py
pyholos/postprocessing/postprocessing.py
pyholos/resources/holos4_cli.zip
pyholos/resources/soil_landscapes_of_canada_v3r2.zip
pyholos/resources/holos/Table_16_Livestock_Coefficients_BeefAndDairy_Cattle_Provider.csv
pyholos/resources/holos/Table_21_Average_Milk_Production_For_Dairy_Cows_By_Province.csv
pyholos/resources/holos/Table_22_Livestock_Coefficients_For_Sheep.csv
pyholos/resources/holos/Table_29_Percentage_Total_Manure_Produced_In_Systems.csv
pyholos/resources/holos/Table_30_Default_Bedding_Material_Composition_Provider.csv
pyholos/resources/holos/Table_50_Fuel_Energy_Requirement_Estimates_By_Region.csv
pyholos/resources/holos/Table_51_Herbicide_Energy_Requirement_Estimates_By_Region.csv
pyholos/resources/holos/Table_61_Fractions_of_dairy_cattle_N_volatilized.csv
pyholos-0.3.1.dist-info/licenses/LICENSE
pyholos-0.3.1.dist-info/METADATA
pyholos-0.3.1.dist-info/WHEEL
pyholos-0.3.1.dist-info/top_level.txt
pyholos-0.3.1.dist-info/RECORD
