Metadata-Version: 2.4
Name: pyholos
Version: 0.3.1
Summary: A Python package for running the HOLOS 4.0 CLI.
Author-email: Rami ALBASHA <ralbasha@msfourrager.com>
Project-URL: Homepage, https://github.com/Mon-Systeme-Fourrager/pyholos
Project-URL: Issues, https://github.com/Mon-Systeme-Fourrager/pyholos/issues
Classifier: Programming Language :: Python :: 3
Classifier: Operating System :: OS Independent
Requires-Python: >=3.12
License-File: LICENSE
Requires-Dist: geojson>=3.1.0
Requires-Dist: shapely>=2.0.6
Requires-Dist: pandas>=2.2.3
Requires-Dist: pydantic>=2.10.6
Dynamic: license-file
